Workbook

Sheet Accounts
A1: Person | B1: Certificate | C1: Inserted | D1: First Day | E1: Replied | F1: Link
A2: Alamin | B2: Yes | C2: =IF(COUNTIF(Master!D:D,A2)>0,"Yes","No") -> Yes | D2: No | E2: No | F2: https://www.instagram.com/alamin.8020ai/
A3: SpiralCon | B3: Yes | C3: =IF(COUNTIF(Master!D:D,A3)>0,"Yes","No") -> Yes | D3: No | E3: No | F3: http://spiralcontent.ai/
A4: umarjamal | B4: Yes | C4: =IF(COUNTIF(Master!D:D,A4)>0,"Yes","No") -> Yes | D4: No | E4: Yes | F4: https://www.instagram.com/uj_umarjamal/
A5: furiouslytech | B5: Yes/No Link | C5: =IF(COUNTIF(Master!D:D,A5)>0,"Yes","No") -> Yes | D5: No | E5: Yes | F5: https://www.instagram.com/furiouslytech/
A6: jerryjhlee | B6: No | C6: =IF(COUNTIF(Master!D:D,A6)>0,"Yes","No") -> No | D6: No | E6: No | F6: https://www.instagram.com/jerryjhlee/?hl=en&g=5
A7: krishnagangwal | B7: Yes | C7: =IF(COUNTIF(Master!D:D,A7)>0,"Yes","No") -> Yes | D7: No | E7: Yes | F7: https://www.instagram.com/krishnagangwal.ai/
A8: itsztales | B8: Yes | C8: =IF(COUNTIF(Master!D:D,A8)>0,"Yes","No") -> Yes | D8: No | E8: No | F8: https://www.instagram.com/itsztales/
A9: sujartech | B9: Yes | C9: =IF(COUNTIF(Master!D:D,A9)>0,"Yes","No") -> Yes | D9: No | E9: Yes | F9: https://www.instagram.com/sujar.tech/
A10: johncorbett | B10: Yes | C10: =IF(COUNTIF(Master!D:D,A10)>0,"Yes","No") -> Yes | D10: No | E10: Yes | F10: https://www.instagram.com/johncorbett777/
A11: matebreton | B11: Yes | C11: =IF(COUNTIF(Master!D:D,A11)>0,"Yes","No") -> No | D11: No | E11: No | F11: https://www.instagram.com/matebreton/?hl=en&g=5
A12: jakemok.io | B12: Yes | C12: =IF(COUNTIF(Master!D:D,A12)>0,"Yes","No") -> Yes | D12: Yes | E12: Yes | F12: https://www.instagram.com/jakemok.io/
A13: David Chen | B13: Yes | C13: =IF(COUNTIF(Master!D:D,A13)>0,"Yes","No") -> No | D13: No | E13: No
A14: jackk_flick | B14: Yes/No specifics | C14: =IF(COUNTIF(Master!D:D,A14)>0,"Yes","No") -> No | D14: Yes | E14: Yes | F14: https://www.instagram.com/jackk_flick/
A15: ai.veerse | B15: Yes | C15: =IF(COUNTIF(Master!D:D,A15)>0,"Yes","No") -> Yes | D15: Yes | E15: Yes | F15: https://www.instagram.com/ai.veerse/
A16: jonesyslifestyle | B16: Yes | C16: =IF(COUNTIF(Master!D:D,A16)>0,"Yes","No") -> Yes | D16: Yes | E16: Yes | F16: https://www.instagram.com/jonesyslifestyle/
A17: pirknn | B17: Yes | C17: =IF(COUNTIF(Master!D:D,A17)>0,"Yes","No") -> Yes | D17: No | E17: Yes | F17: https://www.instagram.com/pirknn/
A18: ssssafin | B18: Yes | C18: =IF(COUNTIF(Master!D:D,A18)>0,"Yes","No") -> Yes | D18: No | E18: No | F18: https://www.instagram.com/ssssafin/
A19: the agi guide | B19: the agi guide | C19: =IF(COUNTIF(Master!D:D,A19)>0,"Yes","No") -> Yes | D19: Yes | E19: Yes | F19: https://www.instagram.com/the.agi.guide/?hl=en&e=5c9b1f10-0ecd-4036-bed8-a4fa3d049e10&g=5
A20: basunverse | B20: basunverse | C20: =IF(COUNTIF(Master!D:D,A20)>0,"Yes","No") -> No | D20: Yes | E20: Yes | F20: https://www.instagram.com/basunverse/?hl=en&e=be78c148-dd09-4136-a0cd-9cf1e4dd6eb6&g=5
A21: cindiezhu | B21: cindiezhu | C21: =IF(COUNTIF(Master!D:D,A21)>0,"Yes","No") -> Yes | D21: Yes | E21: Yes | F21: https://www.instagram.com/cindiezhu/?hl=en&e=f02cf9f9-337a-481e-9b29-934ca3789926&g=5
A22: chase_enloe | B22: chase_enloe | C22: =IF(COUNTIF(Master!D:D,A22)>0,"Yes","No") -> No | D22: No | E22: No | F22: https://www.instagram.com/chase_enloe/
C23: =IF(COUNTIF(Master!D:D,A23)>0,"Yes","No") -> No | D23: No | E23: No
C24: =IF(COUNTIF(Master!D:D,A24)>0,"Yes","No") -> No | D24: No | E24: No

Sheet Delta
A1: IsCertificate | B1: Focus | C1: Original Name | D1: Source (ID) | E1: Fee | F1: Duration To Finish | G1: Link to Certificate | H1: Certificate | I1: Standararized Name | J1: Standarized URL | K1: Certificate ID | L1: Checked | N1: Match Status | O1: Last Verified
A2: Yes | B2: Data Analysis | C2: Deloitte | D2: SpiralCon | E2: 0 | F2: 2 | G2: theforage.com/simulations/deloitte-au/data-analytics-s5zy | I2: =IFERROR(__xludf.DUMMYFUNCTION("IF(C2="""","""",LOWER(TRIM(REGEXREPLACE(C2,""[^A-Za-z0-9 ]"",""""))))"),"deloitte") -> deloitte | J2: =IFERROR(__xludf.DUMMYFUNCTION("IF(G2="""","""",LOWER(REGEXREPLACE(REGEXREPLACE(REGEXREPLACE(G2,""^https?://"",""""),""[?#].*$"",""""),""/+$"","""")))"),"theforage.com/simulations/deloitte-au/data-analytics-s5zy") -> theforage.com/simulations/deloitte-au/data-analytics-s5zy | L2: YES
A3: Yes | B3: Data Analysis | C3: Google Advanced Data Analytics | D3: Alamin | E3: 0 | G3: https://www.coursera.org/professional-certificates/google-advanced-data-analytics | I3: =IFERROR(__xludf.DUMMYFUNCTION("IF(C3="""","""",LOWER(TRIM(REGEXREPLACE(C3,""[^A-Za-z0-9 ]"",""""))))"),"google advanced data analytics") -> google advanced data analytics | J3: =IFERROR(__xludf.DUMMYFUNCTION("IF(G3="""","""",LOWER(REGEXREPLACE(REGEXREPLACE(REGEXREPLACE(G3,""^https?://"",""""),""[?#].*$"",""""),""/+$"","""")))"),"www.coursera.org/professional-certificates/google-advanced-data-analytics") -> www.coursera.org/professional-certificates/google-advanced-data-analytics | L3: YES
A4: Yes | B4: Data Analysis | C4: Google Cybersecurity | D4: Alamin | E4: 0 | G4: https://www.coursera.org/professional-certificates/google-cybersecurity? | I4: =IFERROR(__xludf.DUMMYFUNCTION("IF(C4="""","""",LOWER(TRIM(REGEXREPLACE(C4,""[^A-Za-z0-9 ]"",""""))))"),"google cybersecurity") -> google cybersecurity | J4: =IFERROR(__xludf.DUMMYFUNCTION("IF(G4="""","""",LOWER(REGEXREPLACE(REGEXREPLACE(REGEXREPLACE(G4,""^https?://"",""""),""[?#].*$"",""""),""/+$"","""")))"),"www.coursera.org/professional-certificates/google-cybersecurity") -> www.coursera.org/professional-certificates/google-cybersecurity | L4: YES
A5: Yes | B5: Data Analysis | C5: Google Cloud Certified generative AI Leader | D5: Alamin | E5: 0 | G5: https://cloud.google.com/learn/certification/generative-ai-leader | I5: =IFERROR(__xludf.DUMMYFUNCTION("IF(C5="""","""",LOWER(TRIM(REGEXREPLACE(C5,""[^A-Za-z0-9 ]"",""""))))"),"google cloud certified generative ai leader") -> google cloud certified generative ai leader | J5: =IFERROR(__xludf.DUMMYFUNCTION("IF(G5="""","""",LOWER(REGEXREPLACE(REGEXREPLACE(REGEXREPLACE(G5,""^https?://"",""""),""[?#].*$"",""""),""/+$"","""")))"),"cloud.google.com/learn/certification/generative-ai-leader") -> cloud.google.com/learn/certification/generative-ai-leader | L5: YES
A6: Yes | B6: Data Analysis | C6: Google Crash Course on Python | D6: Alamin | E6: 0 | G6: https://www.coursera.org/professional-certificates/google-it-automation | I6: =IFERROR(__xludf.DUMMYFUNCTION("IF(C6="""","""",LOWER(TRIM(REGEXREPLACE(C6,""[^A-Za-z0-9 ]"",""""))))"),"google crash course on python") -> google crash course on python | J6: =IFERROR(__xludf.DUMMYFUNCTION("IF(G6="""","""",LOWER(REGEXREPLACE(REGEXREPLACE(REGEXREPLACE(G6,""^https?://"",""""),""[?#].*$"",""""),""/+$"","""")))"),"www.coursera.org/professional-certificates/google-it-automation") -> www.coursera.org/professional-certificates/google-it-automation | L6: YES
A7: Yes | B7: AI | C7: Introduction to Generative AI | D7: Alamin | E7: 0 | G7: https://www.coursera.org/learn/introduction-to-generative-ai | I7: =IFERROR(__xludf.DUMMYFUNCTION("IF(C7="""","""",LOWER(TRIM(REGEXREPLACE(C7,""[^A-Za-z0-9 ]"",""""))))"),"introduction to generative ai") -> introduction to generative ai | J7: =IFERROR(__xludf.DUMMYFUNCTION("IF(G7="""","""",LOWER(REGEXREPLACE(REGEXREPLACE(REGEXREPLACE(G7,""^https?://"",""""),""[?#].*$"",""""),""/+$"","""")))"),"www.coursera.org/learn/introduction-to-generative-ai") -> www.coursera.org/learn/introduction-to-generative-ai | L7: YES
A8: Yes | B8: Data Analysis | C8: Agile Project Management | D8: Alamin | E8: 0 | G8: https://www.coursera.org/learn/agile-project-management | I8: =IFERROR(__xludf.DUMMYFUNCTION("IF(C8="""","""",LOWER(TRIM(REGEXREPLACE(C8,""[^A-Za-z0-9 ]"",""""))))"),"agile project management") -> agile project management | J8: =IFERROR(__xludf.DUMMYFUNCTION("IF(G8="""","""",LOWER(REGEXREPLACE(REGEXREPLACE(REGEXREPLACE(G8,""^https?://"",""""),""[?#].*$"",""""),""/+$"","""")))"),"www.coursera.org/learn/agile-project-management") -> www.coursera.org/learn/agile-project-management | L8: YES
A9: Yes | B9: AI | C9: Google AI Essentials | D9: Alamin | E9: 0 | G9: https://www.coursera.org/learn/google-ai-essentials | I9: =IFERROR(__xludf.DUMMYFUNCTION("IF(C9="""","""",LOWER(TRIM(REGEXREPLACE(C9,""[^A-Za-z0-9 ]"",""""))))"),"google ai essentials") -> google ai essentials | J9: =IFERROR(__xludf.DUMMYFUNCTION("IF(G9="""","""",LOWER(REGEXREPLACE(REGEXREPLACE(REGEXREPLACE(G9,""^https?://"",""""),""[?#].*$"",""""),""/+$"","""")))"),"www.coursera.org/learn/google-ai-essentials") -> www.coursera.org/learn/google-ai-essentials | L9: YES
A10: Yes | B10: Machine Learning | C10: kaggle Intro to Machine Course | D10: NA | E10: 0 | G10: https://www.kaggle.com/learn/intro-to-machine-learning | I10: =IFERROR(__xludf.DUMMYFUNCTION("IF(C10="""","""",LOWER(TRIM(REGEXREPLACE(C10,""[^A-Za-z0-9 ]"",""""))))"),"kaggle intro to machine course") -> kaggle intro to machine course | J10: =IFERROR(__xludf.DUMMYFUNCTION("IF(G10="""","""",LOWER(REGEXREPLACE(REGEXREPLACE(REGEXREPLACE(G10,""^https?://"",""""),""[?#].*$"",""""),""/+$"","""")))"),"www.kaggle.com/learn/intro-to-machine-learning") -> www.kaggle.com/learn/intro-to-machine-learning | L10: YES
A11: Yes | C11: KPMG Audit | D11: umarjamal | E11: 0 | F11: 4 | G11: https://www.theforage.com/simulations/kpmg-ca/auditassurance-el6n | I11: =IFERROR(__xludf.DUMMYFUNCTION("IF(C11="""","""",LOWER(TRIM(REGEXREPLACE(C11,""[^A-Za-z0-9 ]"",""""))))"),"kpmg audit") -> kpmg audit | J11: =IFERROR(__xludf.DUMMYFUNCTION("IF(G11="""","""",LOWER(REGEXREPLACE(REGEXREPLACE(REGEXREPLACE(G11,""^https?://"",""""),""[?#].*$"",""""),""/+$"","""")))"),"www.theforage.com/simulations/kpmg-ca/auditassurance-el6n") -> www.theforage.com/simulations/kpmg-ca/auditassurance-el6n | L11: YES
A12: Yes | C12: PWC Audit | D12: umarjamal | E12: 0 | F12: 5 | G12: https://www.theforage.com/simulations/pwc-us/audit-w3fr | I12: =IFERROR(__xludf.DUMMYFUNCTION("IF(C12="""","""",LOWER(TRIM(REGEXREPLACE(C12,""[^A-Za-z0-9 ]"",""""))))"),"pwc audit") -> pwc audit | J12: =IFERROR(__xludf.DUMMYFUNCTION("IF(G12="""","""",LOWER(REGEXREPLACE(REGEXREPLACE(REGEXREPLACE(G12,""^https?://"",""""),""[?#].*$"",""""),""/+$"","""")))"),"www.theforage.com/simulations/pwc-us/audit-w3fr") -> www.theforage.com/simulations/pwc-us/audit-w3fr | L12: YES
A13: Yes | C13: EY Audit | D13: umarjamal | E13: 0 | F13: 5 | G13: https://www.theforage.com/simulations/ey/audit-k5kl | I13: =IFERROR(__xludf.DUMMYFUNCTION("IF(C13="""","""",LOWER(TRIM(REGEXREPLACE(C13,""[^A-Za-z0-9 ]"",""""))))"),"ey audit") -> ey audit | J13: =IFERROR(__xludf.DUMMYFUNCTION("IF(G13="""","""",LOWER(REGEXREPLACE(REGEXREPLACE(REGEXREPLACE(G13,""^https?://"",""""),""[?#].*$"",""""),""/+$"","""")))"),"www.theforage.com/simulations/ey/audit-k5kl") -> www.theforage.com/simulations/ey/audit-k5kl | L13: YES
A14: Yes | C14: EY Technology Risk | D14: umarjamal | E14: 0 | F14: 5 | G14: https://www.theforage.com/simulations/ey/technology-risk-ydqh | I14: =IFERROR(__xludf.DUMMYFUNCTION("IF(C14="""","""",LOWER(TRIM(REGEXREPLACE(C14,""[^A-Za-z0-9 ]"",""""))))"),"ey technology risk") -> ey technology risk | J14: =IFERROR(__xludf.DUMMYFUNCTION("IF(G14="""","""",LOWER(REGEXREPLACE(REGEXREPLACE(REGEXREPLACE(G14,""^https?://"",""""),""[?#].*$"",""""),""/+$"","""")))"),"www.theforage.com/simulations/ey/technology-risk-ydqh") -> www.theforage.com/simulations/ey/technology-risk-ydqh | L14: YES
C15: Deloitte Data Analyst | D15: umarjamal | E15: 0 | F15: 4 | G15: https://www.theforage.com/simulations/deloitte-au/dataanalytics-s5zy | I15: =IFERROR(__xludf.DUMMYFUNCTION("IF(C15="""","""",LOWER(TRIM(REGEXREPLACE(C15,""[^A-Za-z0-9 ]"",""""))))"),"deloitte data analyst") -> deloitte data analyst | J15: =IFERROR(__xludf.DUMMYFUNCTION("IF(G15="""","""",LOWER(REGEXREPLACE(REGEXREPLACE(REGEXREPLACE(G15,""^https?://"",""""),""[?#].*$"",""""),""/+$"","""")))"),"www.theforage.com/simulations/deloitte-au/dataanalytics-s5zy") -> www.theforage.com/simulations/deloitte-au/dataanalytics-s5zy | L15: YES
C16: KPMG Tax Professional | D16: umarjamal | E16: 0 | F16: 5 | G16: https://www.theforage.com/simulations/kpmg-ca/tax-m4t0 | I16: =IFERROR(__xludf.DUMMYFUNCTION("IF(C16="""","""",LOWER(TRIM(REGEXREPLACE(C16,""[^A-Za-z0-9 ]"",""""))))"),"kpmg tax professional") -> kpmg tax professional | J16: =IFERROR(__xludf.DUMMYFUNCTION("IF(G16="""","""",LOWER(REGEXREPLACE(REGEXREPLACE(REGEXREPLACE(G16,""^https?://"",""""),""[?#].*$"",""""),""/+$"","""")))"),"www.theforage.com/simulations/kpmg-ca/tax-m4t0") -> www.theforage.com/simulations/kpmg-ca/tax-m4t0 | L16: YES
C17: PWC Tax Services | D17: umarjamal | E17: 0 | F17: 5 | G17: https://www.theforage.com/simulations/pwc-us/tax-l9rj | I17: =IFERROR(__xludf.DUMMYFUNCTION("IF(C17="""","""",LOWER(TRIM(REGEXREPLACE(C17,""[^A-Za-z0-9 ]"",""""))))"),"pwc tax services") -> pwc tax services | J17: =IFERROR(__xludf.DUMMYFUNCTION("IF(G17="""","""",LOWER(REGEXREPLACE(REGEXREPLACE(REGEXREPLACE(G17,""^https?://"",""""),""[?#].*$"",""""),""/+$"","""")))"),"www.theforage.com/simulations/pwc-us/tax-l9rj") -> www.theforage.com/simulations/pwc-us/tax-l9rj | L17: YES
C18: ACCA Sustainability | D18: umarjamal | E18: 0 | F18: 5 | G18: https://www.theforage.com/simulations/accaapac/sustainability-banking-4sca | I18: =IFERROR(__xludf.DUMMYFUNCTION("IF(C18="""","""",LOWER(TRIM(REGEXREPLACE(C18,""[^A-Za-z0-9 ]"",""""))))"),"acca sustainability") -> acca sustainability | J18: =IFERROR(__xludf.DUMMYFUNCTION("IF(G18="""","""",LOWER(REGEXREPLACE(REGEXREPLACE(REGEXREPLACE(G18,""^https?://"",""""),""[?#].*$"",""""),""/+$"","""")))"),"www.theforage.com/simulations/accaapac/sustainability-banking-4sca") -> www.theforage.com/simulations/accaapac/sustainability-banking-4sca | L18: YES
C19: Goldman Sachs Controllers | D19: umarjamal | E19: 0 | F19: 5 | G19: https://www.theforage.com/simulations/goldmansachs/controllers-8npc | I19: =IFERROR(__xludf.DUMMYFUNCTION("IF(C19="""","""",LOWER(TRIM(REGEXREPLACE(C19,""[^A-Za-z0-9 ]"",""""))))"),"goldman sachs controllers") -> goldman sachs controllers | J19: =IFERROR(__xludf.DUMMYFUNCTION("IF(G19="""","""",LOWER(REGEXREPLACE(REGEXREPLACE(REGEXREPLACE(G19,""^https?://"",""""),""[?#].*$"",""""),""/+$"","""")))"),"www.theforage.com/simulations/goldmansachs/controllers-8npc") -> www.theforage.com/simulations/goldmansachs/controllers-8npc | L19: YES
C20: partnerup professionalism & power | D20: umarjamal | E20: 0 | F20: 5 | G20: https://www.theforage.com/simulations/pnc/professionalism-power-skills-dxef | I20: =IFERROR(__xludf.DUMMYFUNCTION("IF(C20="""","""",LOWER(TRIM(REGEXREPLACE(C20,""[^A-Za-z0-9 ]"",""""))))"),"partnerup professionalism power") -> partnerup professionalism power | J20: =IFERROR(__xludf.DUMMYFUNCTION("IF(G20="""","""",LOWER(REGEXREPLACE(REGEXREPLACE(REGEXREPLACE(G20,""^https?://"",""""),""[?#].*$"",""""),""/+$"","""")))"),"www.theforage.com/simulations/pnc/professionalism-power-skills-dxef") -> www.theforage.com/simulations/pnc/professionalism-power-skills-dxef | L20: YES
A21: Yes | B21: Data Analysis | C21: AWS Skill builder prompt engineering | D21: furiouslytech | E21: 0 | F21: NA | G21: https://skillbuilder.aws/learn/VF6H4SZ1BU/foundations-of-prompt-engineering/7U8XFUVXDT | I21: =IFERROR(__xludf.DUMMYFUNCTION("IF(C21="""","""",LOWER(TRIM(REGEXREPLACE(C21,""[^A-Za-z0-9 ]"",""""))))"),"aws skill builder prompt engineering") -> aws skill builder prompt engineering | J21: =IFERROR(__xludf.DUMMYFUNCTION("IF(G21="""","""",LOWER(REGEXREPLACE(REGEXREPLACE(REGEXREPLACE(G21,""^https?://"",""""),""[?#].*$"",""""),""/+$"","""")))"),"skillbuilder.aws/learn/vf6h4sz1bu/foundations-of-prompt-engineering/7u8xfuvxdt") -> skillbuilder.aws/learn/vf6h4sz1bu/foundations-of-prompt-engineering/7u8xfuvxdt | L21: YES
A22: Yes | C22: Microsoft Introduction to python edx | D22: furiouslytech | E22: 0 | F22: 5 | G22: https://www.edx.org/learn/python/edx-try-it-intro-to-python | I22: =IFERROR(__xludf.DUMMYFUNCTION("IF(C22="""","""",LOWER(TRIM(REGEXREPLACE(C22,""[^A-Za-z0-9 ]"",""""))))"),"microsoft introduction to python edx") -> microsoft introduction to python edx | J22: =IFERROR(__xludf.DUMMYFUNCTION("IF(G22="""","""",LOWER(REGEXREPLACE(REGEXREPLACE(REGEXREPLACE(G22,""^https?://"",""""),""[?#].*$"",""""),""/+$"","""")))"),"www.edx.org/learn/python/edx-try-it-intro-to-python") -> www.edx.org/learn/python/edx-try-it-intro-to-python | L22: YES
A23: Yes | C23: IBM Skillsbuild SQL | D23: furiouslytech | E23: 0 | F23: 6 | G23: https://www.edx.org/learn/data-science/ibm-sql-for-data-science | I23: =IFERROR(__xludf.DUMMYFUNCTION("IF(C23="""","""",LOWER(TRIM(REGEXREPLACE(C23,""[^A-Za-z0-9 ]"",""""))))"),"ibm skillsbuild sql") -> ibm skillsbuild sql | J23: =IFERROR(__xludf.DUMMYFUNCTION("IF(G23="""","""",LOWER(REGEXREPLACE(REGEXREPLACE(REGEXREPLACE(G23,""^https?://"",""""),""[?#].*$"",""""),""/+$"","""")))"),"www.edx.org/learn/data-science/ibm-sql-for-data-science") -> www.edx.org/learn/data-science/ibm-sql-for-data-science | L23: YES
A24: Yes | C24: IBM Data Analysis with Python | D24: furiouslytech | E24: 0 | F24: 8 | G24: https://www.coursera.org/learn/data-analysis-with-python | I24: =IFERROR(__xludf.DUMMYFUNCTION("IF(C24="""","""",LOWER(TRIM(REGEXREPLACE(C24,""[^A-Za-z0-9 ]"",""""))))"),"ibm data analysis with python") -> ibm data analysis with python | J24: =IFERROR(__xludf.DUMMYFUNCTION("IF(G24="""","""",LOWER(REGEXREPLACE(REGEXREPLACE(REGEXREPLACE(G24,""^https?://"",""""),""[?#].*$"",""""),""/+$"","""")))"),"www.coursera.org/learn/data-analysis-with-python") -> www.coursera.org/learn/data-analysis-with-python | L24: YES
A25: Yes | C25: Cisco Networking data science essentials | D25: furiouslytech | E25: 0 | F25: 6 | G25: https://www.netacad.com/courses/data-science-essentials-with-python?courseLang=en-US | I25: =IFERROR(__xludf.DUMMYFUNCTION("IF(C25="""","""",LOWER(TRIM(REGEXREPLACE(C25,""[^A-Za-z0-9 ]"",""""))))"),"cisco networking data science essentials") -> cisco networking data science essentials | J25: =IFERROR(__xludf.DUMMYFUNCTION("IF(G25="""","""",LOWER(REGEXREPLACE(REGEXREPLACE(REGEXREPLACE(G25,""^https?://"",""""),""[?#].*$"",""""),""/+$"","""")))"),"www.netacad.com/courses/data-science-essentials-with-python") -> www.netacad.com/courses/data-science-essentials-with-python | L25: YES
A26: Yes | C26: Datacamp data engineering | D26: furiouslytech | E26: 0 | F26: NA | G26: https://www.datacamp.com/certification/data-engineer | I26: =IFERROR(__xludf.DUMMYFUNCTION("IF(C26="""","""",LOWER(TRIM(REGEXREPLACE(C26,""[^A-Za-z0-9 ]"",""""))))"),"datacamp data engineering") -> datacamp data engineering | J26: =IFERROR(__xludf.DUMMYFUNCTION("IF(G26="""","""",LOWER(REGEXREPLACE(REGEXREPLACE(REGEXREPLACE(G26,""^https?://"",""""),""[?#].*$"",""""),""/+$"","""")))"),"www.datacamp.com/certification/data-engineer") -> www.datacamp.com/certification/data-engineer | L26: YES
A27: Yes | C27: Forage Deloitte Data analytics | D27: furiouslytech | E27: 0 | F27: 4 | G27: https://www.theforage.com/simulations/deloitte-au/dataanalytics-s5zy | I27: =IFERROR(__xludf.DUMMYFUNCTION("IF(C27="""","""",LOWER(TRIM(REGEXREPLACE(C27,""[^A-Za-z0-9 ]"",""""))))"),"forage deloitte data analytics") -> forage deloitte data analytics | J27: =IFERROR(__xludf.DUMMYFUNCTION("IF(G27="""","""",LOWER(REGEXREPLACE(REGEXREPLACE(REGEXREPLACE(G27,""^https?://"",""""),""[?#].*$"",""""),""/+$"","""")))"),"www.theforage.com/simulations/deloitte-au/dataanalytics-s5zy") -> www.theforage.com/simulations/deloitte-au/dataanalytics-s5zy | L27: YES
A28: Yes | C28: Forage Siemens Engineering | D28: furiouslytech | E28: 0 | F28: 4 | G28: https://www.theforage.com/simulations/siemens-mobility/operations-industrial-engineering-xh22 | I28: =IFERROR(__xludf.DUMMYFUNCTION("IF(C28="""","""",LOWER(TRIM(REGEXREPLACE(C28,""[^A-Za-z0-9 ]"",""""))))"),"forage siemens engineering") -> forage siemens engineering | J28: =IFERROR(__xludf.DUMMYFUNCTION("IF(G28="""","""",LOWER(REGEXREPLACE(REGEXREPLACE(REGEXREPLACE(G28,""^https?://"",""""),""[?#].*$"",""""),""/+$"","""")))"),"www.theforage.com/simulations/siemens-mobility/operations-industrial-engineering-xh22") -> www.theforage.com/simulations/siemens-mobility/operations-industrial-engineering-xh22 | L28: YES
A29: Yes | C29: Harvard CS50 Certificate | D29: furiouslytech | E29: 0 | F29: NA | G29: https://cs50.harvard.edu/x/certificate/ | I29: =IFERROR(__xludf.DUMMYFUNCTION("IF(C29="""","""",LOWER(TRIM(REGEXREPLACE(C29,""[^A-Za-z0-9 ]"",""""))))"),"harvard cs50 certificate") -> harvard cs50 certificate | J29: =IFERROR(__xludf.DUMMYFUNCTION("IF(G29="""","""",LOWER(REGEXREPLACE(REGEXREPLACE(REGEXREPLACE(G29,""^https?://"",""""),""[?#].*$"",""""),""/+$"","""")))"),"cs50.harvard.edu/x/certificate") -> cs50.harvard.edu/x/certificate | L29: YES
A30: Yes | C30: Claude Certifed Archtitect | D30: krishnagangwal | G30: https://anthropic-partners.skilljar.com/claude-certified-architect-foundations-certification | I30: =IFERROR(__xludf.DUMMYFUNCTION("IF(C30="""","""",LOWER(TRIM(REGEXREPLACE(C30,""[^A-Za-z0-9 ]"",""""))))"),"claude certifed archtitect") -> claude certifed archtitect | J30: =IFERROR(__xludf.DUMMYFUNCTION("IF(G30="""","""",LOWER(REGEXREPLACE(REGEXREPLACE(REGEXREPLACE(G30,""^https?://"",""""),""[?#].*$"",""""),""/+$"","""")))"),"anthropic-partners.skilljar.com/claude-certified-architect-foundations-certification") -> anthropic-partners.skilljar.com/claude-certified-architect-foundations-certification | L30: YES
A31: Yes | C31: Google AI essentials | D31: krishnagangwal | G31: https://grow.google/ai-essentials/?srsltid=AU7gw4U-100zB_pjoZTFgfOunZ93kYMS4W9UdBNQA7obTkjen6Ozqe4m | I31: =IFERROR(__xludf.DUMMYFUNCTION("IF(C31="""","""",LOWER(TRIM(REGEXREPLACE(C31,""[^A-Za-z0-9 ]"",""""))))"),"google ai essentials") -> google ai essentials | J31: =IFERROR(__xludf.DUMMYFUNCTION("IF(G31="""","""",LOWER(REGEXREPLACE(REGEXREPLACE(REGEXREPLACE(G31,""^https?://"",""""),""[?#].*$"",""""),""/+$"","""")))"),"grow.google/ai-essentials") -> grow.google/ai-essentials | L31: YES
A32: Yes | C32: Oracle OCI AI Foundations Associate | D32: krishnagangwal | G32: https://learn.oracle.com/ols/learning-path/become-an-oci-ai-foundations-associate/146553/163544 | I32: =IFERROR(__xludf.DUMMYFUNCTION("IF(C32="""","""",LOWER(TRIM(REGEXREPLACE(C32,""[^A-Za-z0-9 ]"",""""))))"),"oracle oci ai foundations associate") -> oracle oci ai foundations associate | J32: =IFERROR(__xludf.DUMMYFUNCTION("IF(G32="""","""",LOWER(REGEXREPLACE(REGEXREPLACE(REGEXREPLACE(G32,""^https?://"",""""),""[?#].*$"",""""),""/+$"","""")))"),"learn.oracle.com/ols/learning-path/become-an-oci-ai-foundations-associate/146553/163544") -> learn.oracle.com/ols/learning-path/become-an-oci-ai-foundations-associate/146553/163544 | L32: YES
A33: Yes | C33: AWS Cloud Practitioner Essentials | D33: krishnagangwal | E33: 100 | G33: https://skillbuilder.aws/learn/94T2BEN85A/aws-cloud-practitioner-essentials/8D79F3AVR7 | I33: =IFERROR(__xludf.DUMMYFUNCTION("IF(C33="""","""",LOWER(TRIM(REGEXREPLACE(C33,""[^A-Za-z0-9 ]"",""""))))"),"aws cloud practitioner essentials") -> aws cloud practitioner essentials | J33: =IFERROR(__xludf.DUMMYFUNCTION("IF(G33="""","""",LOWER(REGEXREPLACE(REGEXREPLACE(REGEXREPLACE(G33,""^https?://"",""""),""[?#].*$"",""""),""/+$"","""")))"),"skillbuilder.aws/learn/94t2ben85a/aws-cloud-practitioner-essentials/8d79f3avr7") -> skillbuilder.aws/learn/94t2ben85a/aws-cloud-practitioner-essentials/8d79f3avr7 | L33: YES
A34: Yes | C34: Google Digital marketing | D34: itsztales | G34: www.coursera.org/professional-certificates/google-digital-marketing-ecommerce | I34: =IFERROR(__xludf.DUMMYFUNCTION("IF(C34="""","""",LOWER(TRIM(REGEXREPLACE(C34,""[^A-Za-z0-9 ]"",""""))))"),"google digital marketing") -> google digital marketing | J34: =IFERROR(__xludf.DUMMYFUNCTION("IF(G34="""","""",LOWER(REGEXREPLACE(REGEXREPLACE(REGEXREPLACE(G34,""^https?://"",""""),""[?#].*$"",""""),""/+$"","""")))"),"www.coursera.org/professional-certificates/google-digital-marketing-ecommerce") -> www.coursera.org/professional-certificates/google-digital-marketing-ecommerce | L34: YES
A35: Yes | C35: Google AI Essentials | D35: itsztales | G35: https://www.coursera.org/learn/google-ai-essentials | I35: =IFERROR(__xludf.DUMMYFUNCTION("IF(C35="""","""",LOWER(TRIM(REGEXREPLACE(C35,""[^A-Za-z0-9 ]"",""""))))"),"google ai essentials") -> google ai essentials | J35: =IFERROR(__xludf.DUMMYFUNCTION("IF(G35="""","""",LOWER(REGEXREPLACE(REGEXREPLACE(REGEXREPLACE(G35,""^https?://"",""""),""[?#].*$"",""""),""/+$"","""")))"),"www.coursera.org/learn/google-ai-essentials") -> www.coursera.org/learn/google-ai-essentials | L35: YES
A36: Yes | C36: Google Analytics | D36: itsztales | G36: https://skillshop.docebosaas.com/learn/courses/18609/google-analytics-certification-2026 | I36: =IFERROR(__xludf.DUMMYFUNCTION("IF(C36="""","""",LOWER(TRIM(REGEXREPLACE(C36,""[^A-Za-z0-9 ]"",""""))))"),"google analytics") -> google analytics | J36: =IFERROR(__xludf.DUMMYFUNCTION("IF(G36="""","""",LOWER(REGEXREPLACE(REGEXREPLACE(REGEXREPLACE(G36,""^https?://"",""""),""[?#].*$"",""""),""/+$"","""")))"),"skillshop.docebosaas.com/learn/courses/18609/google-analytics-certification-2026") -> skillshop.docebosaas.com/learn/courses/18609/google-analytics-certification-2026 | L36: YES
A37: Yes | C37: Google Data Analytics | D37: itsztales | G37: https://www.coursera.org/professional-certificates/google-data-analytics | I37: =IFERROR(__xludf.DUMMYFUNCTION("IF(C37="""","""",LOWER(TRIM(REGEXREPLACE(C37,""[^A-Za-z0-9 ]"",""""))))"),"google data analytics") -> google data analytics | J37: =IFERROR(__xludf.DUMMYFUNCTION("IF(G37="""","""",LOWER(REGEXREPLACE(REGEXREPLACE(REGEXREPLACE(G37,""^https?://"",""""),""[?#].*$"",""""),""/+$"","""")))"),"www.coursera.org/professional-certificates/google-data-analytics") -> www.coursera.org/professional-certificates/google-data-analytics | L37: YES
A38: Yes | C38: Google Project Management | D38: itsztales | G38: https://www.coursera.org/professional-certificates/google-project-management | I38: =IFERROR(__xludf.DUMMYFUNCTION("IF(C38="""","""",LOWER(TRIM(REGEXREPLACE(C38,""[^A-Za-z0-9 ]"",""""))))"),"google project management") -> google project management | J38: =IFERROR(__xludf.DUMMYFUNCTION("IF(G38="""","""",LOWER(REGEXREPLACE(REGEXREPLACE(REGEXREPLACE(G38,""^https?://"",""""),""[?#].*$"",""""),""/+$"","""")))"),"www.coursera.org/professional-certificates/google-project-management") -> www.coursera.org/professional-certificates/google-project-management | L38: YES
A39: Yes | C39: HubSpot Content Marketing | D39: itsztales | G39: https://academy.hubspot.com/courses/content-marketing | I39: =IFERROR(__xludf.DUMMYFUNCTION("IF(C39="""","""",LOWER(TRIM(REGEXREPLACE(C39,""[^A-Za-z0-9 ]"",""""))))"),"hubspot content marketing") -> hubspot content marketing | J39: =IFERROR(__xludf.DUMMYFUNCTION("IF(G39="""","""",LOWER(REGEXREPLACE(REGEXREPLACE(REGEXREPLACE(G39,""^https?://"",""""),""[?#].*$"",""""),""/+$"","""")))"),"academy.hubspot.com/courses/content-marketing") -> academy.hubspot.com/courses/content-marketing | L39: YES
A40: Yes | C40: HubSpot Digital Marketing | D40: itsztales | G40: https://academy.hubspot.com/courses/digital-marketing | I40: =IFERROR(__xludf.DUMMYFUNCTION("IF(C40="""","""",LOWER(TRIM(REGEXREPLACE(C40,""[^A-Za-z0-9 ]"",""""))))"),"hubspot digital marketing") -> hubspot digital marketing | J40: =IFERROR(__xludf.DUMMYFUNCTION("IF(G40="""","""",LOWER(REGEXREPLACE(REGEXREPLACE(REGEXREPLACE(G40,""^https?://"",""""),""[?#].*$"",""""),""/+$"","""")))"),"academy.hubspot.com/courses/digital-marketing") -> academy.hubspot.com/courses/digital-marketing | L40: YES
A41: Yes | C41: HubSpot Social Media marketing | D41: itsztales | G41: https://academy.hubspot.com/courses/social-media | I41: =IFERROR(__xludf.DUMMYFUNCTION("IF(C41="""","""",LOWER(TRIM(REGEXREPLACE(C41,""[^A-Za-z0-9 ]"",""""))))"),"hubspot social media marketing") -> hubspot social media marketing | J41: =IFERROR(__xludf.DUMMYFUNCTION("IF(G41="""","""",LOWER(REGEXREPLACE(REGEXREPLACE(REGEXREPLACE(G41,""^https?://"",""""),""[?#].*$"",""""),""/+$"","""")))"),"academy.hubspot.com/courses/social-media") -> academy.hubspot.com/courses/social-media | L41: YES
A42: Yes | C42: HubSpot Email Marketing | D42: itsztales | G42: https://academy.hubspot.com/courses/email-marketing-certification-en | I42: =IFERROR(__xludf.DUMMYFUNCTION("IF(C42="""","""",LOWER(TRIM(REGEXREPLACE(C42,""[^A-Za-z0-9 ]"",""""))))"),"hubspot email marketing") -> hubspot email marketing | J42: =IFERROR(__xludf.DUMMYFUNCTION("IF(G42="""","""",LOWER(REGEXREPLACE(REGEXREPLACE(REGEXREPLACE(G42,""^https?://"",""""),""[?#].*$"",""""),""/+$"","""")))"),"academy.hubspot.com/courses/email-marketing-certification-en") -> academy.hubspot.com/courses/email-marketing-certification-en | L42: YES
A43: Yes | C43: Meta Social Media Marketing | D43: itsztales | G43: https://www.facebook.com/business/learn/social-media-marketing-certificate-coursera | I43: =IFERROR(__xludf.DUMMYFUNCTION("IF(C43="""","""",LOWER(TRIM(REGEXREPLACE(C43,""[^A-Za-z0-9 ]"",""""))))"),"meta social media marketing") -> meta social media marketing | J43: =IFERROR(__xludf.DUMMYFUNCTION("IF(G43="""","""",LOWER(REGEXREPLACE(REGEXREPLACE(REGEXREPLACE(G43,""^https?://"",""""),""[?#].*$"",""""),""/+$"","""")))"),"www.facebook.com/business/learn/social-media-marketing-certificate-coursera") -> www.facebook.com/business/learn/social-media-marketing-certificate-coursera | L43: YES
A44: Yes | C44: Microsoft AI Fundamentals | D44: itsztales | G44: https://learn.microsoft.com/en-us/credentials/certifications/azure-ai-fundamentals/ | I44: =IFERROR(__xludf.DUMMYFUNCTION("IF(C44="""","""",LOWER(TRIM(REGEXREPLACE(C44,""[^A-Za-z0-9 ]"",""""))))"),"microsoft ai fundamentals") -> microsoft ai fundamentals | J44: =IFERROR(__xludf.DUMMYFUNCTION("IF(G44="""","""",LOWER(REGEXREPLACE(REGEXREPLACE(REGEXREPLACE(G44,""^https?://"",""""),""[?#].*$"",""""),""/+$"","""")))"),"learn.microsoft.com/en-us/credentials/certifications/azure-ai-fundamentals") -> learn.microsoft.com/en-us/credentials/certifications/azure-ai-fundamentals | L44: YES
A45: Yes | C45: Microsoft Power BI | D45: itsztales | G45: www.coursera.org/professional-certificates/microsoft-power-bi-data-analyst | I45: =IFERROR(__xludf.DUMMYFUNCTION("IF(C45="""","""",LOWER(TRIM(REGEXREPLACE(C45,""[^A-Za-z0-9 ]"",""""))))"),"microsoft power bi") -> microsoft power bi | J45: =IFERROR(__xludf.DUMMYFUNCTION("IF(G45="""","""",LOWER(REGEXREPLACE(REGEXREPLACE(REGEXREPLACE(G45,""^https?://"",""""),""[?#].*$"",""""),""/+$"","""")))"),"www.coursera.org/professional-certificates/microsoft-power-bi-data-analyst") -> www.coursera.org/professional-certificates/microsoft-power-bi-data-analyst | L45: YES
A46: Yes | C46: Microsoft Azure Fundamentals | D46: itsztales | G46: https://www.coursera.org/specializations/microsoft-azure-fundamentals-az900-exam-prep | I46: =IFERROR(__xludf.DUMMYFUNCTION("IF(C46="""","""",LOWER(TRIM(REGEXREPLACE(C46,""[^A-Za-z0-9 ]"",""""))))"),"microsoft azure fundamentals") -> microsoft azure fundamentals | J46: =IFERROR(__xludf.DUMMYFUNCTION("IF(G46="""","""",LOWER(REGEXREPLACE(REGEXREPLACE(REGEXREPLACE(G46,""^https?://"",""""),""[?#].*$"",""""),""/+$"","""")))"),"www.coursera.org/specializations/microsoft-azure-fundamentals-az900-exam-prep") -> www.coursera.org/specializations/microsoft-azure-fundamentals-az900-exam-prep | L46: YES
A47: Yes | C47: Career Essentials in Generative AI | D47: itsztales | G47: https://www.linkedin.com/learning/paths/career-essentials-in-generative-ai-by-microsoft-and-linkedin | I47: =IFERROR(__xludf.DUMMYFUNCTION("IF(C47="""","""",LOWER(TRIM(REGEXREPLACE(C47,""[^A-Za-z0-9 ]"",""""))))"),"career essentials in generative ai") -> career essentials in generative ai | J47: =IFERROR(__xludf.DUMMYFUNCTION("IF(G47="""","""",LOWER(REGEXREPLACE(REGEXREPLACE(REGEXREPLACE(G47,""^https?://"",""""),""[?#].*$"",""""),""/+$"","""")))"),"www.linkedin.com/learning/paths/career-essentials-in-generative-ai-by-microsoft-and-linkedin") -> www.linkedin.com/learning/paths/career-essentials-in-generative-ai-by-microsoft-and-linkedin | L47: YES
A48: Yes | C48: IBM Data Science | D48: itsztales | G48: https://www.coursera.org/professional-certificates/ibm-data-science?utm_medium=sem&utm_source=gg&utm_campaign=b2c_apac_ibm-data-science_ibm_ftcof_professional-certificates_cx_dr_bau_gg_sem_pr_s3_en_m_hyb_24-05_x&campaignid=21260288546&adgroupid=161508822226&device=c&keyword=ibm%20data%20science&matchtype=p&network=g&devicemodel=&creativeid=698924747646&assetgroupid=&targetid=kwd-312859523693&extensionid=&placement=&gad_source=1&gad_campaignid=21260288546&gclid=CjwKCAjwxeHWBhBPEiwAiqtQ-RpUT_ZGlCDSp9K3kxSDmxfi1LmWlsN1s9aS9kZV5op1XyTz-gb3VxoCKZEQAvD_BwE | I48: =IFERROR(__xludf.DUMMYFUNCTION("IF(C48="""","""",LOWER(TRIM(REGEXREPLACE(C48,""[^A-Za-z0-9 ]"",""""))))"),"ibm data science") -> ibm data science | J48: =IFERROR(__xludf.DUMMYFUNCTION("IF(G48="""","""",LOWER(REGEXREPLACE(REGEXREPLACE(REGEXREPLACE(G48,""^https?://"",""""),""[?#].*$"",""""),""/+$"","""")))"),"www.coursera.org/professional-certificates/ibm-data-science") -> www.coursera.org/professional-certificates/ibm-data-science | L48: YES
A49: Yes | C49: IBM AI Fundamentals | D49: itsztales | G49: https://www.netacad.com/courses/ai-ibm-skillsbuild?courseLang=en-US | I49: =IFERROR(__xludf.DUMMYFUNCTION("IF(C49="""","""",LOWER(TRIM(REGEXREPLACE(C49,""[^A-Za-z0-9 ]"",""""))))"),"ibm ai fundamentals") -> ibm ai fundamentals | J49: =IFERROR(__xludf.DUMMYFUNCTION("IF(G49="""","""",LOWER(REGEXREPLACE(REGEXREPLACE(REGEXREPLACE(G49,""^https?://"",""""),""[?#].*$"",""""),""/+$"","""")))"),"www.netacad.com/courses/ai-ibm-skillsbuild") -> www.netacad.com/courses/ai-ibm-skillsbuild | L49: YES
A50: Yes | C50: freeCodeCamp responsive Web Design | D50: itsztales | G50: https://www.freecodecamp.org/learn/responsive-web-design-v9/ | I50: =IFERROR(__xludf.DUMMYFUNCTION("IF(C50="""","""",LOWER(TRIM(REGEXREPLACE(C50,""[^A-Za-z0-9 ]"",""""))))"),"freecodecamp responsive web design") -> freecodecamp responsive web design | J50: =IFERROR(__xludf.DUMMYFUNCTION("IF(G50="""","""",LOWER(REGEXREPLACE(REGEXREPLACE(REGEXREPLACE(G50,""^https?://"",""""),""[?#].*$"",""""),""/+$"","""")))"),"www.freecodecamp.org/learn/responsive-web-design-v9") -> www.freecodecamp.org/learn/responsive-web-design-v9 | L50: YES
A51: Yes | C51: freeCodeCamp JavaScript | D51: itsztales | G51: https://www.freecodecamp.org/learn/javascript-v9/ | I51: =IFERROR(__xludf.DUMMYFUNCTION("IF(C51="""","""",LOWER(TRIM(REGEXREPLACE(C51,""[^A-Za-z0-9 ]"",""""))))"),"freecodecamp javascript") -> freecodecamp javascript | J51: =IFERROR(__xludf.DUMMYFUNCTION("IF(G51="""","""",LOWER(REGEXREPLACE(REGEXREPLACE(REGEXREPLACE(G51,""^https?://"",""""),""[?#].*$"",""""),""/+$"","""")))"),"www.freecodecamp.org/learn/javascript-v9") -> www.freecodecamp.org/learn/javascript-v9 | L51: YES
A52: Yes | C52: freeCodeCamp Data Visualisation | D52: itsztales | G52: https://www.freecodecamp.org/learn/data-visualization/ | I52: =IFERROR(__xludf.DUMMYFUNCTION("IF(C52="""","""",LOWER(TRIM(REGEXREPLACE(C52,""[^A-Za-z0-9 ]"",""""))))"),"freecodecamp data visualisation") -> freecodecamp data visualisation | J52: =IFERROR(__xludf.DUMMYFUNCTION("IF(G52="""","""",LOWER(REGEXREPLACE(REGEXREPLACE(REGEXREPLACE(G52,""^https?://"",""""),""[?#].*$"",""""),""/+$"","""")))"),"www.freecodecamp.org/learn/data-visualization") -> www.freecodecamp.org/learn/data-visualization | L52: YES
A53: Yes | C53: Python for Everybody | D53: itsztales | G53: https://www.coursera.org/specializations/python | I53: =IFERROR(__xludf.DUMMYFUNCTION("IF(C53="""","""",LOWER(TRIM(REGEXREPLACE(C53,""[^A-Za-z0-9 ]"",""""))))"),"python for everybody") -> python for everybody | J53: =IFERROR(__xludf.DUMMYFUNCTION("IF(G53="""","""",LOWER(REGEXREPLACE(REGEXREPLACE(REGEXREPLACE(G53,""^https?://"",""""),""[?#].*$"",""""),""/+$"","""")))"),"www.coursera.org/specializations/python") -> www.coursera.org/specializations/python | L53: YES
A54: Yes | C54: Excel Skills for Business | D54: itsztales | G54: https://www.coursera.org/specializations/excel | I54: =IFERROR(__xludf.DUMMYFUNCTION("IF(C54="""","""",LOWER(TRIM(REGEXREPLACE(C54,""[^A-Za-z0-9 ]"",""""))))"),"excel skills for business") -> excel skills for business | J54: =IFERROR(__xludf.DUMMYFUNCTION("IF(G54="""","""",LOWER(REGEXREPLACE(REGEXREPLACE(REGEXREPLACE(G54,""^https?://"",""""),""[?#].*$"",""""),""/+$"","""")))"),"www.coursera.org/specializations/excel") -> www.coursera.org/specializations/excel | L54: YES
A55: Yes | C55: Introduction to cybersecurity | D55: itsztales | G55: https://www.netacad.com/courses/introduction-to-cybersecurity | I55: =IFERROR(__xludf.DUMMYFUNCTION("IF(C55="""","""",LOWER(TRIM(REGEXREPLACE(C55,""[^A-Za-z0-9 ]"",""""))))"),"introduction to cybersecurity") -> introduction to cybersecurity | J55: =IFERROR(__xludf.DUMMYFUNCTION("IF(G55="""","""",LOWER(REGEXREPLACE(REGEXREPLACE(REGEXREPLACE(G55,""^https?://"",""""),""[?#].*$"",""""),""/+$"","""")))"),"www.netacad.com/courses/introduction-to-cybersecurity") -> www.netacad.com/courses/introduction-to-cybersecurity | L55: YES
A56: Yes | C56: UX Design Fundamentals | D56: itsztales | G56: https://www.coursera.org/specializations/ui-ux-design?utm_medium=sem&utm_source=gg&utm_campaign=b2c_apac_x_multi_ftcof_x_cx_dr_bau_gg_sem_pr_s3_en_m_hyb_26-09_consolidated-s3-others&campaignid=24314885422&adgroupid=201707340858&device=c&keyword=ux%20design%20course&matchtype=p&network=g&devicemodel=&creativeid=826595554549&assetgroupid=&targetid=kwd-25742925511&extensionid=&placement=&gad_source=1&gad_campaignid=24314885422&gclid=CjwKCAjwxeHWBhBPEiwAiqtQ-QfBMsg-8G9szPkBFfDmTxllslx6tAs9eEe9hjbYJ_-PgYocX6UoTBoClIEQAvD_BwE | I56: =IFERROR(__xludf.DUMMYFUNCTION("IF(C56="""","""",LOWER(TRIM(REGEXREPLACE(C56,""[^A-Za-z0-9 ]"",""""))))"),"ux design fundamentals") -> ux design fundamentals | J56: =IFERROR(__xludf.DUMMYFUNCTION("IF(G56="""","""",LOWER(REGEXREPLACE(REGEXREPLACE(REGEXREPLACE(G56,""^https?://"",""""),""[?#].*$"",""""),""/+$"","""")))"),"www.coursera.org/specializations/ui-ux-design") -> www.coursera.org/specializations/ui-ux-design | L56: YES
A57: Yes | C57: Financial Markets | D57: itsztales | G57: https://www.coursera.org/learn/financial-markets-global | I57: =IFERROR(__xludf.DUMMYFUNCTION("IF(C57="""","""",LOWER(TRIM(REGEXREPLACE(C57,""[^A-Za-z0-9 ]"",""""))))"),"financial markets") -> financial markets | J57: =IFERROR(__xludf.DUMMYFUNCTION("IF(G57="""","""",LOWER(REGEXREPLACE(REGEXREPLACE(REGEXREPLACE(G57,""^https?://"",""""),""[?#].*$"",""""),""/+$"","""")))"),"www.coursera.org/learn/financial-markets-global") -> www.coursera.org/learn/financial-markets-global | L57: YES
A58: Yes | B58: Development | C58: Microsoft Foundational C# | D58: sujartech | G58: https://www.freecodecamp.org/learn/foundational-c-sharp-with-microsoft/ | I58: =IFERROR(__xludf.DUMMYFUNCTION("IF(C58="""","""",LOWER(TRIM(REGEXREPLACE(C58,""[^A-Za-z0-9 ]"",""""))))"),"microsoft foundational c") -> microsoft foundational c | J58: =IFERROR(__xludf.DUMMYFUNCTION("IF(G58="""","""",LOWER(REGEXREPLACE(REGEXREPLACE(REGEXREPLACE(G58,""^https?://"",""""),""[?#].*$"",""""),""/+$"","""")))"),"www.freecodecamp.org/learn/foundational-c-sharp-with-microsoft") -> www.freecodecamp.org/learn/foundational-c-sharp-with-microsoft | L58: YES
A59: Yes | B59: Data Analysis | C59: Kaggle Machine learning | D59: sujartech | G59: https://www.kaggle.com/learn/intro-to-machine-learning | I59: =IFERROR(__xludf.DUMMYFUNCTION("IF(C59="""","""",LOWER(TRIM(REGEXREPLACE(C59,""[^A-Za-z0-9 ]"",""""))))"),"kaggle machine learning") -> kaggle machine learning | J59: =IFERROR(__xludf.DUMMYFUNCTION("IF(G59="""","""",LOWER(REGEXREPLACE(REGEXREPLACE(REGEXREPLACE(G59,""^https?://"",""""),""[?#].*$"",""""),""/+$"","""")))"),"www.kaggle.com/learn/intro-to-machine-learning") -> www.kaggle.com/learn/intro-to-machine-learning | L59: YES
A60: Yes | B60: SQL | C60: HackerRank SQL Basic | D60: sujartech | G60: https://www.hackerrank.com/skills-verification/sql_basic | I60: =IFERROR(__xludf.DUMMYFUNCTION("IF(C60="""","""",LOWER(TRIM(REGEXREPLACE(C60,""[^A-Za-z0-9 ]"",""""))))"),"hackerrank sql basic") -> hackerrank sql basic | J60: =IFERROR(__xludf.DUMMYFUNCTION("IF(G60="""","""",LOWER(REGEXREPLACE(REGEXREPLACE(REGEXREPLACE(G60,""^https?://"",""""),""[?#].*$"",""""),""/+$"","""")))"),"www.hackerrank.com/skills-verification/sql_basic") -> www.hackerrank.com/skills-verification/sql_basic | L60: YES
A61: Yes | B61: AI | C61: Elements of AI | D61: sujartech | G61: https://course.elementsofai.com/ | I61: =IFERROR(__xludf.DUMMYFUNCTION("IF(C61="""","""",LOWER(TRIM(REGEXREPLACE(C61,""[^A-Za-z0-9 ]"",""""))))"),"elements of ai") -> elements of ai | J61: =IFERROR(__xludf.DUMMYFUNCTION("IF(G61="""","""",LOWER(REGEXREPLACE(REGEXREPLACE(REGEXREPLACE(G61,""^https?://"",""""),""[?#].*$"",""""),""/+$"","""")))"),"course.elementsofai.com") -> course.elementsofai.com | L61: YES
A62: Yes | B62: Development | C62: IBM Introduction to Cloud | D62: sujartech | G62: https://cognitiveclass.ai/courses/introduction-to-cloud | I62: =IFERROR(__xludf.DUMMYFUNCTION("IF(C62="""","""",LOWER(TRIM(REGEXREPLACE(C62,""[^A-Za-z0-9 ]"",""""))))"),"ibm introduction to cloud") -> ibm introduction to cloud | J62: =IFERROR(__xludf.DUMMYFUNCTION("IF(G62="""","""",LOWER(REGEXREPLACE(REGEXREPLACE(REGEXREPLACE(G62,""^https?://"",""""),""[?#].*$"",""""),""/+$"","""")))"),"cognitiveclass.ai/courses/introduction-to-cloud") -> cognitiveclass.ai/courses/introduction-to-cloud | L62: YES
A63: Yes | B63: Development | C63: Saylor C++ Programming | D63: sujartech | G63: https://learn.saylor.org/course/cs107 | I63: =IFERROR(__xludf.DUMMYFUNCTION("IF(C63="""","""",LOWER(TRIM(REGEXREPLACE(C63,""[^A-Za-z0-9 ]"",""""))))"),"saylor c programming") -> saylor c programming | J63: =IFERROR(__xludf.DUMMYFUNCTION("IF(G63="""","""",LOWER(REGEXREPLACE(REGEXREPLACE(REGEXREPLACE(G63,""^https?://"",""""),""[?#].*$"",""""),""/+$"","""")))"),"learn.saylor.org/course/cs107") -> learn.saylor.org/course/cs107 | L63: YES
A64: Yes | B64: Business | C64: JPMorganChase Investment | D64: johncorbett | F64: 4 | G64: https://www.theforage.com/simulations/jpmorgan/investment-banking-hkyd | I64: =IFERROR(__xludf.DUMMYFUNCTION("IF(C64="""","""",LOWER(TRIM(REGEXREPLACE(C64,""[^A-Za-z0-9 ]"",""""))))"),"jpmorganchase investment") -> jpmorganchase investment | J64: =IFERROR(__xludf.DUMMYFUNCTION("IF(G64="""","""",LOWER(REGEXREPLACE(REGEXREPLACE(REGEXREPLACE(G64,""^https?://"",""""),""[?#].*$"",""""),""/+$"","""")))"),"www.theforage.com/simulations/jpmorgan/investment-banking-hkyd") -> www.theforage.com/simulations/jpmorgan/investment-banking-hkyd | L64: YES
A65: Yes | B65: Business | C65: Bank of America Investment Banking | D65: johncorbett | F65: 5 | G65: https://www.theforage.com/simulations/bank-of-america/investment-banking-bwp7 | I65: =IFERROR(__xludf.DUMMYFUNCTION("IF(C65="""","""",LOWER(TRIM(REGEXREPLACE(C65,""[^A-Za-z0-9 ]"",""""))))"),"bank of america investment banking") -> bank of america investment banking | J65: =IFERROR(__xludf.DUMMYFUNCTION("IF(G65="""","""",LOWER(REGEXREPLACE(REGEXREPLACE(REGEXREPLACE(G65,""^https?://"",""""),""[?#].*$"",""""),""/+$"","""")))"),"www.theforage.com/simulations/bank-of-america/investment-banking-bwp7") -> www.theforage.com/simulations/bank-of-america/investment-banking-bwp7 | L65: YES
A66: Yes | B66: Business | C66: Goldman Sachs Controllers | D66: johncorbett | F66: 1 | G66: https://www.theforage.com/simulations/goldmansachs/controllers-8npc | I66: =IFERROR(__xludf.DUMMYFUNCTION("IF(C66="""","""",LOWER(TRIM(REGEXREPLACE(C66,""[^A-Za-z0-9 ]"",""""))))"),"goldman sachs controllers") -> goldman sachs controllers | J66: =IFERROR(__xludf.DUMMYFUNCTION("IF(G66="""","""",LOWER(REGEXREPLACE(REGEXREPLACE(REGEXREPLACE(G66,""^https?://"",""""),""[?#].*$"",""""),""/+$"","""")))"),"www.theforage.com/simulations/goldmansachs/controllers-8npc") -> www.theforage.com/simulations/goldmansachs/controllers-8npc | L66: YES
A67: Yes | B67: Business | C67: Citi Investment Banking | D67: johncorbett | F67: 6 | G67: https://www.theforage.com/simulations/citi/investment-banking-9wcw | I67: =IFERROR(__xludf.DUMMYFUNCTION("IF(C67="""","""",LOWER(TRIM(REGEXREPLACE(C67,""[^A-Za-z0-9 ]"",""""))))"),"citi investment banking") -> citi investment banking | J67: =IFERROR(__xludf.DUMMYFUNCTION("IF(G67="""","""",LOWER(REGEXREPLACE(REGEXREPLACE(REGEXREPLACE(G67,""^https?://"",""""),""[?#].*$"",""""),""/+$"","""")))"),"www.theforage.com/simulations/citi/investment-banking-9wcw") -> www.theforage.com/simulations/citi/investment-banking-9wcw | L67: YES
A68: Yes | B68: Business | C68: H2 Ventures Venture Capital | D68: johncorbett | F68: 4 | G68: https://www.theforage.com/simulations/h2-ventures/venture-capital-comi | I68: =IFERROR(__xludf.DUMMYFUNCTION("IF(C68="""","""",LOWER(TRIM(REGEXREPLACE(C68,""[^A-Za-z0-9 ]"",""""))))"),"h2 ventures venture capital") -> h2 ventures venture capital | J68: =IFERROR(__xludf.DUMMYFUNCTION("IF(G68="""","""",LOWER(REGEXREPLACE(REGEXREPLACE(REGEXREPLACE(G68,""^https?://"",""""),""[?#].*$"",""""),""/+$"","""")))"),"www.theforage.com/simulations/h2-ventures/venture-capital-comi") -> www.theforage.com/simulations/h2-ventures/venture-capital-comi | L68: YES
A69: Yes | B69: Business | C69: BCG Strategy Consulting | D69: johncorbett | F69: 5 | G69: https://www.theforage.com/simulations/bcg/strategy-consulting-jk76 | I69: =IFERROR(__xludf.DUMMYFUNCTION("IF(C69="""","""",LOWER(TRIM(REGEXREPLACE(C69,""[^A-Za-z0-9 ]"",""""))))"),"bcg strategy consulting") -> bcg strategy consulting | J69: =IFERROR(__xludf.DUMMYFUNCTION("IF(G69="""","""",LOWER(REGEXREPLACE(REGEXREPLACE(REGEXREPLACE(G69,""^https?://"",""""),""[?#].*$"",""""),""/+$"","""")))"),"www.theforage.com/simulations/bcg/strategy-consulting-jk76") -> www.theforage.com/simulations/bcg/strategy-consulting-jk76 | L69: YES
A70: Yes | B70: Data Analysis | C70: mastercard Advisor & Consulting Services | D70: johncorbett | F70: 2 | G70: https://www.theforage.com/simulations/mastercard/advisors-client-services-xvlw | I70: =IFERROR(__xludf.DUMMYFUNCTION("IF(C70="""","""",LOWER(TRIM(REGEXREPLACE(C70,""[^A-Za-z0-9 ]"",""""))))"),"mastercard advisor consulting services") -> mastercard advisor consulting services | J70: =IFERROR(__xludf.DUMMYFUNCTION("IF(G70="""","""",LOWER(REGEXREPLACE(REGEXREPLACE(REGEXREPLACE(G70,""^https?://"",""""),""[?#].*$"",""""),""/+$"","""")))"),"www.theforage.com/simulations/mastercard/advisors-client-services-xvlw") -> www.theforage.com/simulations/mastercard/advisors-client-services-xvlw | L70: YES
A71: Yes | B71: Business | C71: BCG Digital Transformation | D71: johncorbett | F71: 4 | G71: https://www.theforage.com/simulations/bcg/digital-transformation-pk18 | I71: =IFERROR(__xludf.DUMMYFUNCTION("IF(C71="""","""",LOWER(TRIM(REGEXREPLACE(C71,""[^A-Za-z0-9 ]"",""""))))"),"bcg digital transformation") -> bcg digital transformation | J71: =IFERROR(__xludf.DUMMYFUNCTION("IF(G71="""","""",LOWER(REGEXREPLACE(REGEXREPLACE(REGEXREPLACE(G71,""^https?://"",""""),""[?#].*$"",""""),""/+$"","""")))"),"www.theforage.com/simulations/bcg/digital-transformation-pk18") -> www.theforage.com/simulations/bcg/digital-transformation-pk18 | L71: YES
A72: Yes | B72: Business | C72: CBRE Project management | D72: johncorbett | F72: 2 | G72: https://www.theforage.com/simulations/cbre/project-management-x2vz | I72: =IFERROR(__xludf.DUMMYFUNCTION("IF(C72="""","""",LOWER(TRIM(REGEXREPLACE(C72,""[^A-Za-z0-9 ]"",""""))))"),"cbre project management") -> cbre project management | J72: =IFERROR(__xludf.DUMMYFUNCTION("IF(G72="""","""",LOWER(REGEXREPLACE(REGEXREPLACE(REGEXREPLACE(G72,""^https?://"",""""),""[?#].*$"",""""),""/+$"","""")))"),"www.theforage.com/simulations/cbre/project-management-x2vz") -> www.theforage.com/simulations/cbre/project-management-x2vz | L72: YES
A73: Yes | B73: Business | C73: Siemens Mobility Project Manager | D73: johncorbett | F73: 2 | G73: https://www.theforage.com/simulations/siemens-mobility/project-management-qydx | I73: =IFERROR(__xludf.DUMMYFUNCTION("IF(C73="""","""",LOWER(TRIM(REGEXREPLACE(C73,""[^A-Za-z0-9 ]"",""""))))"),"siemens mobility project manager") -> siemens mobility project manager | J73: =IFERROR(__xludf.DUMMYFUNCTION("IF(G73="""","""",LOWER(REGEXREPLACE(REGEXREPLACE(REGEXREPLACE(G73,""^https?://"",""""),""[?#].*$"",""""),""/+$"","""")))"),"www.theforage.com/simulations/siemens-mobility/project-management-qydx") -> www.theforage.com/simulations/siemens-mobility/project-management-qydx | L73: YES
A74: Yes | B74: Business | C74: Red Bull On-Premise Sales | D74: johncorbett | F74: 2 | G74: https://www.theforage.com/simulations/red-bull/on-premise-sales-waza | I74: =IFERROR(__xludf.DUMMYFUNCTION("IF(C74="""","""",LOWER(TRIM(REGEXREPLACE(C74,""[^A-Za-z0-9 ]"",""""))))"),"red bull onpremise sales") -> red bull onpremise sales | J74: =IFERROR(__xludf.DUMMYFUNCTION("IF(G74="""","""",LOWER(REGEXREPLACE(REGEXREPLACE(REGEXREPLACE(G74,""^https?://"",""""),""[?#].*$"",""""),""/+$"","""")))"),"www.theforage.com/simulations/red-bull/on-premise-sales-waza") -> www.theforage.com/simulations/red-bull/on-premise-sales-waza | L74: YES
A75: Yes | B75: Business | C75: Pearson Marketing Explorer | D75: johncorbett | F75: NA | G75: https://www.theforage.com/simulations/pearson/marketing-oxce | I75: =IFERROR(__xludf.DUMMYFUNCTION("IF(C75="""","""",LOWER(TRIM(REGEXREPLACE(C75,""[^A-Za-z0-9 ]"",""""))))"),"pearson marketing explorer") -> pearson marketing explorer | J75: =IFERROR(__xludf.DUMMYFUNCTION("IF(G75="""","""",LOWER(REGEXREPLACE(REGEXREPLACE(REGEXREPLACE(G75,""^https?://"",""""),""[?#].*$"",""""),""/+$"","""")))"),"www.theforage.com/simulations/pearson/marketing-oxce") -> www.theforage.com/simulations/pearson/marketing-oxce | L75: YES
A76: Yes | B76: Business | C76: Forage Academy Omnichannel Marketing | D76: johncorbett | F76: 6 | G76: https://www.theforage.com/simulations/forage/sponsored-content-omnichannel-marketing-5iep | I76: =IFERROR(__xludf.DUMMYFUNCTION("IF(C76="""","""",LOWER(TRIM(REGEXREPLACE(C76,""[^A-Za-z0-9 ]"",""""))))"),"forage academy omnichannel marketing") -> forage academy omnichannel marketing | J76: =IFERROR(__xludf.DUMMYFUNCTION("IF(G76="""","""",LOWER(REGEXREPLACE(REGEXREPLACE(REGEXREPLACE(G76,""^https?://"",""""),""[?#].*$"",""""),""/+$"","""")))"),"www.theforage.com/simulations/forage/sponsored-content-omnichannel-marketing-5iep") -> www.theforage.com/simulations/forage/sponsored-content-omnichannel-marketing-5iep | L76: YES
A77: Yes | B77: Business | C77: Bloomberg Client Engagement | D77: johncorbett | F77: 4 | G77: https://www.theforage.com/simulations/bloomberg/client-engagement-a6hi | I77: =IFERROR(__xludf.DUMMYFUNCTION("IF(C77="""","""",LOWER(TRIM(REGEXREPLACE(C77,""[^A-Za-z0-9 ]"",""""))))"),"bloomberg client engagement") -> bloomberg client engagement | J77: =IFERROR(__xludf.DUMMYFUNCTION("IF(G77="""","""",LOWER(REGEXREPLACE(REGEXREPLACE(REGEXREPLACE(G77,""^https?://"",""""),""[?#].*$"",""""),""/+$"","""")))"),"www.theforage.com/simulations/bloomberg/client-engagement-a6hi") -> www.theforage.com/simulations/bloomberg/client-engagement-a6hi | L77: YES
A78: Yes | B78: Business | C78: Hewlett Packard Enerprise Digital Sales | D78: johncorbett | F78: 5 | G78: https://www.theforage.com/simulations/hewlett-packard-enterprise/digital-sales-mmkg | I78: =IFERROR(__xludf.DUMMYFUNCTION("IF(C78="""","""",LOWER(TRIM(REGEXREPLACE(C78,""[^A-Za-z0-9 ]"",""""))))"),"hewlett packard enerprise digital sales") -> hewlett packard enerprise digital sales | J78: =IFERROR(__xludf.DUMMYFUNCTION("IF(G78="""","""",LOWER(REGEXREPLACE(REGEXREPLACE(REGEXREPLACE(G78,""^https?://"",""""),""[?#].*$"",""""),""/+$"","""")))"),"www.theforage.com/simulations/hewlett-packard-enterprise/digital-sales-mmkg") -> www.theforage.com/simulations/hewlett-packard-enterprise/digital-sales-mmkg | L78: YES
C79: Walmart Advanced Software Engineering | D79: johncorbett | F79: 4 | G79: https://www.theforage.com/simulations/walmart/software-engineering-fceb | I79: =IFERROR(__xludf.DUMMYFUNCTION("IF(C79="""","""",LOWER(TRIM(REGEXREPLACE(C79,""[^A-Za-z0-9 ]"",""""))))"),"walmart advanced software engineering") -> walmart advanced software engineering | J79: =IFERROR(__xludf.DUMMYFUNCTION("IF(G79="""","""",LOWER(REGEXREPLACE(REGEXREPLACE(REGEXREPLACE(G79,""^https?://"",""""),""[?#].*$"",""""),""/+$"","""")))"),"www.theforage.com/simulations/walmart/software-engineering-fceb") -> www.theforage.com/simulations/walmart/software-engineering-fceb | L79: YES
C80: JPMorganChase Software Engineering | D80: johncorbett | F80: 5 | G80: https://www.theforage.com/simulations/jpmorgan/advanced-software-engineering-r0fm | I80: =IFERROR(__xludf.DUMMYFUNCTION("IF(C80="""","""",LOWER(TRIM(REGEXREPLACE(C80,""[^A-Za-z0-9 ]"",""""))))"),"jpmorganchase software engineering") -> jpmorganchase software engineering | J80: =IFERROR(__xludf.DUMMYFUNCTION("IF(G80="""","""",LOWER(REGEXREPLACE(REGEXREPLACE(REGEXREPLACE(G80,""^https?://"",""""),""[?#].*$"",""""),""/+$"","""")))"),"www.theforage.com/simulations/jpmorgan/advanced-software-engineering-r0fm") -> www.theforage.com/simulations/jpmorgan/advanced-software-engineering-r0fm | L80: YES
C81: Skyscanner Front-End Software Engineering | D81: johncorbett | F81: 2 | G81: https://www.theforage.com/simulations/skyscanner/front-end-software-engineering-cbwl | I81: =IFERROR(__xludf.DUMMYFUNCTION("IF(C81="""","""",LOWER(TRIM(REGEXREPLACE(C81,""[^A-Za-z0-9 ]"",""""))))"),"skyscanner frontend software engineering") -> skyscanner frontend software engineering | J81: =IFERROR(__xludf.DUMMYFUNCTION("IF(G81="""","""",LOWER(REGEXREPLACE(REGEXREPLACE(REGEXREPLACE(G81,""^https?://"",""""),""[?#].*$"",""""),""/+$"","""")))"),"www.theforage.com/simulations/skyscanner/front-end-software-engineering-cbwl") -> www.theforage.com/simulations/skyscanner/front-end-software-engineering-cbwl | L81: YES
C82: Mastercard Cybersecurity | D82: johncorbett | F82: 2 | G82: https://www.theforage.com/simulations/mastercard/cybersecurity-t8ye | I82: =IFERROR(__xludf.DUMMYFUNCTION("IF(C82="""","""",LOWER(TRIM(REGEXREPLACE(C82,""[^A-Za-z0-9 ]"",""""))))"),"mastercard cybersecurity") -> mastercard cybersecurity | J82: =IFERROR(__xludf.DUMMYFUNCTION("IF(G82="""","""",LOWER(REGEXREPLACE(REGEXREPLACE(REGEXREPLACE(G82,""^https?://"",""""),""[?#].*$"",""""),""/+$"","""")))"),"www.theforage.com/simulations/mastercard/cybersecurity-t8ye") -> www.theforage.com/simulations/mastercard/cybersecurity-t8ye | L82: YES
C83: BCG Data Science | D83: johncorbett | F83: 9 | G83: https://www.theforage.com/simulations/bcg/data-science-ccdz | I83: =IFERROR(__xludf.DUMMYFUNCTION("IF(C83="""","""",LOWER(TRIM(REGEXREPLACE(C83,""[^A-Za-z0-9 ]"",""""))))"),"bcg data science") -> bcg data science | J83: =IFERROR(__xludf.DUMMYFUNCTION("IF(G83="""","""",LOWER(REGEXREPLACE(REGEXREPLACE(REGEXREPLACE(G83,""^https?://"",""""),""[?#].*$"",""""),""/+$"","""")))"),"www.theforage.com/simulations/bcg/data-science-ccdz") -> www.theforage.com/simulations/bcg/data-science-ccdz | L83: YES
C84: Tata GenAI-Powered Data Analytics | D84: johncorbett | F84: NA | G84: https://www.theforage.com/simulations/tata/data-analytics-t3zr | I84: =IFERROR(__xludf.DUMMYFUNCTION("IF(C84="""","""",LOWER(TRIM(REGEXREPLACE(C84,""[^A-Za-z0-9 ]"",""""))))"),"tata genaipowered data analytics") -> tata genaipowered data analytics | J84: =IFERROR(__xludf.DUMMYFUNCTION("IF(G84="""","""",LOWER(REGEXREPLACE(REGEXREPLACE(REGEXREPLACE(G84,""^https?://"",""""),""[?#].*$"",""""),""/+$"","""")))"),"www.theforage.com/simulations/tata/data-analytics-t3zr") -> www.theforage.com/simulations/tata/data-analytics-t3zr | L84: YES
C85: Oracle OCI AI Foundations Associate | D85: jakemok.io | E85: 0 | F85: 25 | G85: https://learn.oracle.com/ols/learning-path/become-an-oci-ai-foundations-associate/146553/163544 | I85: =IFERROR(__xludf.DUMMYFUNCTION("IF(C85="""","""",LOWER(TRIM(REGEXREPLACE(C85,""[^A-Za-z0-9 ]"",""""))))"),"oracle oci ai foundations associate") -> oracle oci ai foundations associate | J85: =IFERROR(__xludf.DUMMYFUNCTION("IF(G85="""","""",LOWER(REGEXREPLACE(REGEXREPLACE(REGEXREPLACE(G85,""^https?://"",""""),""[?#].*$"",""""),""/+$"","""")))"),"learn.oracle.com/ols/learning-path/become-an-oci-ai-foundations-associate/146553/163544") -> learn.oracle.com/ols/learning-path/become-an-oci-ai-foundations-associate/146553/163544 | L85: YES
C86: GitHub Foundations | D86: jakemok.io | E86: 0 | F86: NA | G86: https://examregistration.github.com/certification/GHF | I86: =IFERROR(__xludf.DUMMYFUNCTION("IF(C86="""","""",LOWER(TRIM(REGEXREPLACE(C86,""[^A-Za-z0-9 ]"",""""))))"),"github foundations") -> github foundations | J86: =IFERROR(__xludf.DUMMYFUNCTION("IF(G86="""","""",LOWER(REGEXREPLACE(REGEXREPLACE(REGEXREPLACE(G86,""^https?://"",""""),""[?#].*$"",""""),""/+$"","""")))"),"examregistration.github.com/certification/ghf") -> examregistration.github.com/certification/ghf | L86: YES
C87: Cisco Introduction to Cybersecurity | D87: jakemok.io | E87: 0 | F87: 6 | G87: https://www.netacad.com/courses/introduction-to-cybersecurity | I87: =IFERROR(__xludf.DUMMYFUNCTION("IF(C87="""","""",LOWER(TRIM(REGEXREPLACE(C87,""[^A-Za-z0-9 ]"",""""))))"),"cisco introduction to cybersecurity") -> cisco introduction to cybersecurity | J87: =IFERROR(__xludf.DUMMYFUNCTION("IF(G87="""","""",LOWER(REGEXREPLACE(REGEXREPLACE(REGEXREPLACE(G87,""^https?://"",""""),""[?#].*$"",""""),""/+$"","""")))"),"www.netacad.com/courses/introduction-to-cybersecurity") -> www.netacad.com/courses/introduction-to-cybersecurity | L87: YES
C88: IBM SkillsBuild: Getting Started with Cybersecurity | D88: jakemok.io | E88: 0 | F88: 3 | G88: https://skillsbuild.org/college-students/course-catalog/getting-started-with-cybersecurity | I88: =IFERROR(__xludf.DUMMYFUNCTION("IF(C88="""","""",LOWER(TRIM(REGEXREPLACE(C88,""[^A-Za-z0-9 ]"",""""))))"),"ibm skillsbuild getting started with cybersecurity") -> ibm skillsbuild getting started with cybersecurity | J88: =IFERROR(__xludf.DUMMYFUNCTION("IF(G88="""","""",LOWER(REGEXREPLACE(REGEXREPLACE(REGEXREPLACE(G88,""^https?://"",""""),""[?#].*$"",""""),""/+$"","""")))"),"skillsbuild.org/college-students/course-catalog/getting-started-with-cybersecurity") -> skillsbuild.org/college-students/course-catalog/getting-started-with-cybersecurity | L88: YES
C89: Microsoft Applied Skills | D89: jakemok.io | E89: 0 | F89: NA | G89: https://learn.microsoft.com/en-us/credentials/applied-skills/ | I89: =IFERROR(__xludf.DUMMYFUNCTION("IF(C89="""","""",LOWER(TRIM(REGEXREPLACE(C89,""[^A-Za-z0-9 ]"",""""))))"),"microsoft applied skills") -> microsoft applied skills | J89: =IFERROR(__xludf.DUMMYFUNCTION("IF(G89="""","""",LOWER(REGEXREPLACE(REGEXREPLACE(REGEXREPLACE(G89,""^https?://"",""""),""[?#].*$"",""""),""/+$"","""")))"),"learn.microsoft.com/en-us/credentials/applied-skills") -> learn.microsoft.com/en-us/credentials/applied-skills | L89: YES
C90: Harvard CS50 Certificate | D90: jakemok.io | E90: 0 | F90: NA | G90: https://cs50.harvard.edu/x/certificate/ | I90: =IFERROR(__xludf.DUMMYFUNCTION("IF(C90="""","""",LOWER(TRIM(REGEXREPLACE(C90,""[^A-Za-z0-9 ]"",""""))))"),"harvard cs50 certificate") -> harvard cs50 certificate | J90: =IFERROR(__xludf.DUMMYFUNCTION("IF(G90="""","""",LOWER(REGEXREPLACE(REGEXREPLACE(REGEXREPLACE(G90,""^https?://"",""""),""[?#].*$"",""""),""/+$"","""")))"),"cs50.harvard.edu/x/certificate") -> cs50.harvard.edu/x/certificate | L90: YES
C91: HubSpot Inbound Certification | D91: jakemok.io | E91: 0 | F91: NA | G91: https://academy.hubspot.com/courses/inbound | I91: =IFERROR(__xludf.DUMMYFUNCTION("IF(C91="""","""",LOWER(TRIM(REGEXREPLACE(C91,""[^A-Za-z0-9 ]"",""""))))"),"hubspot inbound certification") -> hubspot inbound certification | J91: =IFERROR(__xludf.DUMMYFUNCTION("IF(G91="""","""",LOWER(REGEXREPLACE(REGEXREPLACE(REGEXREPLACE(G91,""^https?://"",""""),""[?#].*$"",""""),""/+$"","""")))"),"academy.hubspot.com/courses/inbound") -> academy.hubspot.com/courses/inbound | L91: YES
C92: AWS Cloud Quest: Cloud Practitioner | D92: jakemok.io | E92: 0 | F92: 12 | G92: https://skillbuilder.aws/learn/FU5WCYVGKY/aws-cloud-quest-cloud-practitioner/JF9TKU68GT | I92: =IFERROR(__xludf.DUMMYFUNCTION("IF(C92="""","""",LOWER(TRIM(REGEXREPLACE(C92,""[^A-Za-z0-9 ]"",""""))))"),"aws cloud quest cloud practitioner") -> aws cloud quest cloud practitioner | J92: =IFERROR(__xludf.DUMMYFUNCTION("IF(G92="""","""",LOWER(REGEXREPLACE(REGEXREPLACE(REGEXREPLACE(G92,""^https?://"",""""),""[?#].*$"",""""),""/+$"","""")))"),"skillbuilder.aws/learn/fu5wcyvgky/aws-cloud-quest-cloud-practitioner/jf9tku68gt") -> skillbuilder.aws/learn/fu5wcyvgky/aws-cloud-quest-cloud-practitioner/jf9tku68gt | L92: YES
C93: Kaggle Intro to SQL | D93: jakemok.io | E93: 0 | F93: 3 | G93: https://www.kaggle.com/learn/intro-to-sql | I93: =IFERROR(__xludf.DUMMYFUNCTION("IF(C93="""","""",LOWER(TRIM(REGEXREPLACE(C93,""[^A-Za-z0-9 ]"",""""))))"),"kaggle intro to sql") -> kaggle intro to sql | J93: =IFERROR(__xludf.DUMMYFUNCTION("IF(G93="""","""",LOWER(REGEXREPLACE(REGEXREPLACE(REGEXREPLACE(G93,""^https?://"",""""),""[?#].*$"",""""),""/+$"","""")))"),"www.kaggle.com/learn/intro-to-sql") -> www.kaggle.com/learn/intro-to-sql | L93: YES
C94: Kaggle Intro to Machine Learning | D94: jakemok.io | E94: 0 | F94: 3 | G94: https://www.kaggle.com/learn/intro-to-machine-learning | I94: =IFERROR(__xludf.DUMMYFUNCTION("IF(C94="""","""",LOWER(TRIM(REGEXREPLACE(C94,""[^A-Za-z0-9 ]"",""""))))"),"kaggle intro to machine learning") -> kaggle intro to machine learning | J94: =IFERROR(__xludf.DUMMYFUNCTION("IF(G94="""","""",LOWER(REGEXREPLACE(REGEXREPLACE(REGEXREPLACE(G94,""^https?://"",""""),""[?#].*$"",""""),""/+$"","""")))"),"www.kaggle.com/learn/intro-to-machine-learning") -> www.kaggle.com/learn/intro-to-machine-learning | L94: YES
C95: Kaggle Python / Pandas | D95: jakemok.io | E95: 0 | F95: 5 | G95: https://www.kaggle.com/learn/python | I95: =IFERROR(__xludf.DUMMYFUNCTION("IF(C95="""","""",LOWER(TRIM(REGEXREPLACE(C95,""[^A-Za-z0-9 ]"",""""))))"),"kaggle python pandas") -> kaggle python pandas | J95: =IFERROR(__xludf.DUMMYFUNCTION("IF(G95="""","""",LOWER(REGEXREPLACE(REGEXREPLACE(REGEXREPLACE(G95,""^https?://"",""""),""[?#].*$"",""""),""/+$"","""")))"),"www.kaggle.com/learn/python") -> www.kaggle.com/learn/python | L95: YES
C96: Databricks Lakehouse Fundamentals | D96: jakemok.io | E96: 0 | F96: 1 | G96: https://www.databricks.com/learn/certification/lakehouse-platform-fundamentals | I96: =IFERROR(__xludf.DUMMYFUNCTION("IF(C96="""","""",LOWER(TRIM(REGEXREPLACE(C96,""[^A-Za-z0-9 ]"",""""))))"),"databricks lakehouse fundamentals") -> databricks lakehouse fundamentals | J96: =IFERROR(__xludf.DUMMYFUNCTION("IF(G96="""","""",LOWER(REGEXREPLACE(REGEXREPLACE(REGEXREPLACE(G96,""^https?://"",""""),""[?#].*$"",""""),""/+$"","""")))"),"www.databricks.com/learn/certification/lakehouse-platform-fundamentals") -> www.databricks.com/learn/certification/lakehouse-platform-fundamentals | L96: YES
C97: Databricks AI Agent Fundamentals | D97: jakemok.io | E97: 0 | F97: 1.5 | G97: https://www.databricks.com/learn/training/certification | I97: =IFERROR(__xludf.DUMMYFUNCTION("IF(C97="""","""",LOWER(TRIM(REGEXREPLACE(C97,""[^A-Za-z0-9 ]"",""""))))"),"databricks ai agent fundamentals") -> databricks ai agent fundamentals | J97: =IFERROR(__xludf.DUMMYFUNCTION("IF(G97="""","""",LOWER(REGEXREPLACE(REGEXREPLACE(REGEXREPLACE(G97,""^https?://"",""""),""[?#].*$"",""""),""/+$"","""")))"),"www.databricks.com/learn/training/certification") -> www.databricks.com/learn/training/certification | L97: YES
C98: IBM SkillsBuild: Cloud Computing Fundamentals | D98: jakemok.io | E98: 0 | F98: 10 | G98: https://skillsbuild.org/college-students/course-catalog/ | I98: =IFERROR(__xludf.DUMMYFUNCTION("IF(C98="""","""",LOWER(TRIM(REGEXREPLACE(C98,""[^A-Za-z0-9 ]"",""""))))"),"ibm skillsbuild cloud computing fundamentals") -> ibm skillsbuild cloud computing fundamentals | J98: =IFERROR(__xludf.DUMMYFUNCTION("IF(G98="""","""",LOWER(REGEXREPLACE(REGEXREPLACE(REGEXREPLACE(G98,""^https?://"",""""),""[?#].*$"",""""),""/+$"","""")))"),"skillsbuild.org/college-students/course-catalog") -> skillsbuild.org/college-students/course-catalog | L98: YES
C99: Google Cloud skill badge (one/month) | D99: jakemok.io | E99: 0 | F99: NA | G99: https://www.skills.google/ | I99: =IFERROR(__xludf.DUMMYFUNCTION("IF(C99="""","""",LOWER(TRIM(REGEXREPLACE(C99,""[^A-Za-z0-9 ]"",""""))))"),"google cloud skill badge onemonth") -> google cloud skill badge onemonth | J99: =IFERROR(__xludf.DUMMYFUNCTION("IF(G99="""","""",LOWER(REGEXREPLACE(REGEXREPLACE(REGEXREPLACE(G99,""^https?://"",""""),""[?#].*$"",""""),""/+$"","""")))"),"www.skills.google") -> www.skills.google | L99: YES
C100: AWS Cloud Practitioner Essentials | D100: jakemok.io | E100: 0 | F100: 13 | G100: https://skillbuilder.aws/learn/FU5WCYVGKY/aws-cloud-quest-cloud-practitioner/JF9TKU68GT | I100: =IFERROR(__xludf.DUMMYFUNCTION("IF(C100="""","""",LOWER(TRIM(REGEXREPLACE(C100,""[^A-Za-z0-9 ]"",""""))))"),"aws cloud practitioner essentials") -> aws cloud practitioner essentials | J100: =IFERROR(__xludf.DUMMYFUNCTION("IF(G100="""","""",LOWER(REGEXREPLACE(REGEXREPLACE(REGEXREPLACE(G100,""^https?://"",""""),""[?#].*$"",""""),""/+$"","""")))"),"skillbuilder.aws/learn/fu5wcyvgky/aws-cloud-quest-cloud-practitioner/jf9tku68gt") -> skillbuilder.aws/learn/fu5wcyvgky/aws-cloud-quest-cloud-practitioner/jf9tku68gt | L100: YES
...

Sheet Certificates
A1: Certificate ID | B1: Standardized Name | C1: Provider | D1: Focus | E1: Official Course URL | F1: Fee (Ringgit) | G1: Duration (Hours)
A2: 1 | B2: Forage Deloitte Data analytics | C2: Deloitte | D2: Data & Analysis | E2: theforage.com/simulations/deloitte-au/data-analytics-s5zy | F2: 0 | G2: 2
A3: 2 | B3: Kaggle Intro to Machine Course | C3: Kaggle | D3: Data & Analysis | E3: https://www.kaggle.com/learn/intro-to-machine-learning | F3: 0 | G3: NA
A4: 3 | B4: Kaggle Intro to SQL | C4: Kaggle | D4: Data & Analysis | E4: https://www.kaggle.com/learn/intro-to-sql | F4: 0 | G4: NA
A5: 4 | B5: Kaggle Python / Pandas | C5: Kaggle | D5: Data & Analysis | E5: https://www.kaggle.com/learn/python | F5: 0 | G5: NA
A6: 5 | B6: Anthropic AI Fluency: Framework & Foundations | C6: Anthropic | D6: AI | E6: https://anthropic.skilljar.com/ai-fluency-framework-foundations | F6: 0 | G6: NA
A7: 6 | B7: Claude Certifed Archtitect | C7: Anthropic | D7: AI | E7: https://anthropic-partners.skilljar.com/claude-certified-architect-foundations-certification | F7: 0 | G7: NA
A8: 7 | B8: Anthropic, Building effective human-agent teams | C8: Anthropic | D8: AI | E8: https://academy.claude.com/courses/building-effective-human-agent-teams | F8: 0 | G8: NA
A9: 8 | B9: Anthropic, Claude Platform 101. | C9: Anthropic | D9: AI | E9: https://academy.claude.com/courses/claude-platform-101 | F9: 0 | G9: NA
A10: 9 | B10: Anthropic, Model Context Protocol: Advanced topics. | C10: Anthropic | D10: Software & IT | E10: https://academy.claude.com/courses/model-context-protocol-advanced-topics | F10: 0 | G10: NA
A11: 10 | B11: Microsoft Applied Skills | C11: Microsoft | D11: Others | E11: https://learn.microsoft.com/en-us/credentials/applied-skills/ | F11: 0 | G11: NA
A12: 11 | B12: Goldman Sachs Controllers | C12: Goldman | D12: Finance & Accounting | E12: https://www.theforage.com/simulations/goldmansachs/controllers-8npc | F12: 0 | G12: NA
A13: 12 | B13: EY Audit | C13: EY | D13: Finance & Accounting | E13: https://www.theforage.com/simulations/ey/audit-k5kl | F13: 0 | G13: NA
A14: 13 | B14: EY Technology Risk | C14: EY | D14: Cybersecurity | E14: https://www.theforage.com/simulations/ey/technology-risk-ydqh | F14: 0 | G14: NA
... A129: 128 | B129: Agile Project Management | C129: Google | D129: Business & Management | E129: https://www.coursera.org/learn/agile-project-management | F129: 0 | G129: NA

Sheet Master
A1: IsCertificate | B1: Focus | C1: Original Name | D1: Source (ID) | E1: Link to Certificate | F1: Certificate ID
A2: Yes | B2: {=IF(F2="","",_xlfn.XLOOKUP(F2,Certificates!A:A,Certificates!D:D,"No match",0))} -> Data & Analysis | C2: Forage Deloitte Data analytics | D2: SpiralCon | E2: theforage.com/simulations/deloitte-au/data-analytics-s5zy | F2: {=IF(C2="","",_xlfn.XLOOKUP(C2,Certificates!B:B,Certificates!A:A,"No match",0))} -> 1
A3: Yes | B3: {=IF(F3="","",_xlfn.XLOOKUP(F3,Certificates!A:A,Certificates!D:D,"No match",0))} -> Data & Analysis | C3: Google Advanced Data Analytics | D3: Alamin | E3: https://www.coursera.org/professional-certificates/google-advanced-data-analytics | F3: {=IF(C3="","",_xlfn.XLOOKUP(C3,Certificates!B:B,Certificates!A:A,"No match",0))} -> 29
A4: Yes | B4: {=IF(F4="","",_xlfn.XLOOKUP(F4,Certificates!A:A,Certificates!D:D,"No match",0))} -> Cybersecurity | C4: Google Cybersecurity | D4: Alamin | E4: https://www.coursera.org/professional-certificates/google-cybersecurity? | F4: {=IF(C4="","",_xlfn.XLOOKUP(C4,Certificates!B:B,Certificates!A:A,"No match",0))} -> 30
A5: Yes | B5: {=IF(F5="","",_xlfn.XLOOKUP(F5,Certificates!A:A,Certificates!D:D,"No match",0))} -> AI | C5: Google Cloud Certified generative AI Leader | D5: Alamin | E5: https://cloud.google.com/learn/certification/generative-ai-leader | F5: {=IF(C5="","",_xlfn.XLOOKUP(C5,Certificates!B:B,Certificates!A:A,"No match",0))} -> 31
A6: Yes | B6: {=IF(F6="","",_xlfn.XLOOKUP(F6,Certificates!A:A,Certificates!D:D,"No match",0))} -> Software & IT | C6: Google Crash Course on Python | D6: Alamin | E6: https://www.coursera.org/professional-certificates/google-it-automation | F6: {=IF(C6="","",_xlfn.XLOOKUP(C6,Certificates!B:B,Certificates!A:A,"No match",0))} -> 32
A7: Yes | B7: {=IF(F7="","",_xlfn.XLOOKUP(F7,Certificates!A:A,Certificates!D:D,"No match",0))} -> AI | C7: Introduction to Generative AI | D7: Alamin | E7: https://www.coursera.org/learn/introduction-to-generative-ai | F7: {=IF(C7="","",_xlfn.XLOOKUP(C7,Certificates!B:B,Certificates!A:A,"No match",0))} -> 127
A8: Yes | B8: {=IF(F8="","",_xlfn.XLOOKUP(F8,Certificates!A:A,Certificates!D:D,"No match",0))} -> Business & Management | C8: Agile Project Management | D8: Alamin | E8: https://www.coursera.org/learn/agile-project-management | F8: {=IF(C8="","",_xlfn.XLOOKUP(C8,Certificates!B:B,Certificates!A:A,"No match",0))} -> 128
A9: Yes | B9: {=IF(F9="","",_xlfn.XLOOKUP(F9,Certificates!A:A,Certificates!D:D,"No match",0))} -> AI | C9: Google AI Essentials | D9: Alamin | E9: https://www.coursera.org/learn/google-ai-essentials | F9: {=IF(C9="","",_xlfn.XLOOKUP(C9,Certificates!B:B,Certificates!A:A,"No match",0))} -> 28
A10: Yes | B10: {=IF(F10="","",_xlfn.XLOOKUP(F10,Certificates!A:A,Certificates!D:D,"No match",0))} -> Finance & Accounting | C10: KPMG Audit | D10: umarjamal | E10: https://www.theforage.com/simulations/kpmg-ca/auditassurance-el6n | F10: {=IF(C10="","",_xlfn.XLOOKUP(C10,Certificates!B:B,Certificates!A:A,"No match",0))} -> 50
A11: Yes | B11: {=IF(F11="","",_xlfn.XLOOKUP(F11,Certificates!A:A,Certificates!D:D,"No match",0))} -> Finance & Accounting | C11: PWC Audit | D11: umarjamal | E11: https://www.theforage.com/simulations/pwc-us/audit-w3fr | F11: {=IF(C11="","",_xlfn.XLOOKUP(C11,Certificates!B:B,Certificates!A:A,"No match",0))} -> 52
A12: Yes | B12: {=IF(F12="","",_xlfn.XLOOKUP(F12,Certificates!A:A,Certificates!D:D,"No match",0))} -> Finance & Accounting | C12: EY Audit | D12: umarjamal | E12: https://www.theforage.com/simulations/ey/audit-k5kl | F12: {=IF(C12="","",_xlfn.XLOOKUP(C12,Certificates!B:B,Certificates!A:A,"No match",0))} -> 12
A13: Yes | B13: {=IF(F13="","",_xlfn.XLOOKUP(F13,Certificates!A:A,Certificates!D:D,"No match",0))} -> Cybersecurity | C13: EY Technology Risk | D13: umarjamal | E13: https://www.theforage.com/simulations/ey/technology-risk-ydqh | F13: {=IF(C13="","",_xlfn.XLOOKUP(C13,Certificates!B:B,Certificates!A:A,"No match",0))} -> 13
... A157: Yes | B157: {=IF(F157="","",_xlfn.XLOOKUP(F157,Certificates!A:A,Certificates!D:D,"No match",0))} -> AI | C157: AI Leadership | D157: cindiezhu | E157: https://academy.openai.com/public/courses/ai-leadership-kaf7k | F157: {=IF(C157="","",_xlfn.XLOOKUP(C157,Certificates!B:B,Certificates!A:A,"No match",0))} -> 76
F158: {=IF(C158="","",_xlfn.XLOOKUP(C158,Certificates!B:B,Certificates!A:A,"No match",0))}
